stacklet/mcp/__init__.py
stacklet/mcp/__main__.py
stacklet/mcp/cmdline.py
stacklet/mcp/lifespan.py
stacklet/mcp/mcp.py
stacklet/mcp/mcp_info.md
stacklet/mcp/server.py
stacklet/mcp/settings.py
stacklet/mcp/stacklet_auth.py
stacklet/mcp/assetdb/__init__.py
stacklet/mcp/assetdb/models.py
stacklet/mcp/assetdb/redash.py
stacklet/mcp/assetdb/sql_info.md
stacklet/mcp/assetdb/tools.py
stacklet/mcp/docs/__init__.py
stacklet/mcp/docs/client.py
stacklet/mcp/docs/models.py
stacklet/mcp/docs/tools.py
stacklet/mcp/platform/__init__.py
stacklet/mcp/platform/dataset_info.md
stacklet/mcp/platform/graphql.py
stacklet/mcp/platform/graphql_info.md
stacklet/mcp/platform/models.py
stacklet/mcp/platform/tools.py
stacklet/mcp/utils/__init__.py
stacklet/mcp/utils/file.py
stacklet/mcp/utils/json.py
stacklet/mcp/utils/mcp_json.py
stacklet/mcp/utils/text.py
stacklet/mcp/utils/tool.py
stacklet_mcp-0.1.1.dist-info/METADATA
stacklet_mcp-0.1.1.dist-info/WHEEL
stacklet_mcp-0.1.1.dist-info/entry_points.txt
stacklet_mcp-0.1.1.dist-info/RECORD
