Metadata-Version: 2.4
Name: stacklet-mcp
Version: 0.1.1
Summary: MCP server for the Stacklet environment
Classifier: Programming Language :: Python :: 3 :: Only
Classifier: Programming Language :: Python :: 3.12
Classifier: Programming Language :: Python :: 3.13
Requires-Python: >=3.12
Requires-Dist: fastmcp>=2
Requires-Dist: graphql-core>=3.2
Requires-Dist: httpx>=0.28.1
Requires-Dist: pydantic-settings>=2.10.1
Requires-Dist: pydantic>=2.11.7
